assistant/__init__.py
assistant/assistant.py
assistant/chat.py
assistant/openai_assistant.py
config/__init__.py
config/config.py
iox/__init__.py
iox/iox_wrapper.py
nucore/__init__.py
nucore/cmd.py
nucore/condition.py
nucore/editor.py
nucore/linkdef.py
nucore/loader.py
nucore/node.py
nucore/nodedef.py
nucore/nucore.py
nucore/nucore_backend_api.py
nucore/nucore_error.py
nucore/nucore_programs.py
nucore/profile.py
nucore/schedule.py
nucore/uom.py
nucore_ai-1.1.5.dist-info/licenses/LICENSE
prompts/__init__.py
rag/__init__.py
rag/device_rag_formatter.py
rag/embedder.py
rag/rag_data_struct.py
rag/rag_db.py
rag/rag_formatter.py
rag/rag_processor.py
rag/reranker.py
rag/static_info_rag_formatter.py
rag/tools_rag_formatter.py
server/start_servers.py
nucore_ai-1.1.5.dist-info/METADATA
nucore_ai-1.1.5.dist-info/WHEEL
nucore_ai-1.1.5.dist-info/top_level.txt
nucore_ai-1.1.5.dist-info/RECORD
