Metadata-Version: 2.4
Name: nucore-ai
Version: 1.1.5
Summary: Lightweight library for command/control/optimization/automation of smart home devices using LLMs
Author-email: Michel Kohanim <michel@universal-devices.com>, "P.A. SCHEMBRI" <pa.schembri@advanced-stack.com>
License-Expression: MIT
Project-URL: Homepage, https://github.com/NuCoreAI/nucore-ai.git
License-File: LICENSE
Requires-Dist: requests
Requires-Dist: numpy
Requires-Dist: httpx
Requires-Dist: hnswlib
Requires-Dist: APScheduler<4.0,>=3.10
Requires-Dist: astral>=2.2
Requires-Dist: aiohttp>=3.9
Requires-Dist: pytest-asyncio
Requires-Dist: fastapi
Requires-Dist: websockets
Requires-Dist: uvicorn
Dynamic: license-file
